statictypes/__init__.py
statictypes/type_check.py
statictypes-0.0.2.dist-info/LICENSE
statictypes-0.0.2.dist-info/METADATA
statictypes-0.0.2.dist-info/WHEEL
statictypes-0.0.2.dist-info/top_level.txt
statictypes-0.0.2.dist-info/RECORD
