Metadata-Version: 2.1
Name: statictypes
Version: 0.0.2
Summary: Enforce type annotations
Home-page: https://github.com/eriksholmlund/statictypes
Author: Erik Schytt Holmlund
Author-email: erik-holmlund@hotmail.com
License: UNKNOWN
Platform: UNKNOWN
Classifier: Programming Language :: Python :: 3
Classifier: License :: OSI Approved :: Apache Software License
Classifier: Operating System :: OS Independent
Requires-Python: >=3.6
